bpm2fps/__init__.py
bpm2fps/__main__.py
bpm2fps/app.qml
bpm2fps/cli.py
bpm2fps/gui.py
bpm2fps/usd.py
bpm2fps-1.0.2.dist-info/LICENSE
bpm2fps-1.0.2.dist-info/METADATA
bpm2fps-1.0.2.dist-info/WHEEL
bpm2fps-1.0.2.dist-info/entry_points.txt
bpm2fps-1.0.2.dist-info/top_level.txt
bpm2fps-1.0.2.dist-info/RECORD
