Metadata-Version: 2.1
Name: bpm2fps
Version: 1.0.2
Summary: Convert beats per minute to animation frames.
Home-page: https://github.com/BreadMakesYouFull/bpm2fps.git
Author: BreadMakesYouFull
License: MIT
Keywords: fps bpm calculate calculator usd animation anim reference
Classifier: Topic :: Artistic Software
Classifier: Topic :: Multimedia :: Graphics :: 3D Modeling
Classifier: Topic :: Multimedia :: Graphics
Classifier: Programming Language :: Python
Classifier: Programming Language :: Python :: 3
Classifier: Programming Language :: Python :: 3 :: Only
Classifier: Topic :: Education
Classifier: Topic :: Scientific/Engineering :: Mathematics
Classifier: Intended Audience :: Education
Classifier: License :: OSI Approved :: MIT License
License-File: LICENSE
Provides-Extra: gui
Requires-Dist: pyside6 ; extra == 'gui'
